README.md
setup.py
corvidData/__init__.py
corvidData/test.py
corvidData/twi_data.py
corvidData.egg-info/PKG-INFO
corvidData.egg-info/SOURCES.txt
corvidData.egg-info/dependency_links.txt
corvidData.egg-info/requires.txt
corvidData.egg-info/top_level.txt