Metadata-Version: 2.1
Name: corvidData
Version: 0.0.1
Summary: A python package for download corvid twi dataset
Home-page: https://github.com/corvid-ai/data-repo/
Author: Prof Nick
Author-email: nickadamu@gmail.com
License: MIT
Platform: UNKNOWN
Classifier: License :: OSI Approved :: MIT License
Classifier: Programming Language :: Python
Classifier: Programming Language :: Python :: 3
Classifier: Programming Language :: Python :: 3.6
Classifier: Programming Language :: Python :: Implementation :: CPython
Classifier: Programming Language :: Python :: Implementation :: PyPy
Requires-Python: >=3.6.0
